{
  "ID": 682,
  "key": "group_63894140af6e3",
  "title": "_Component-Options",
  "fields": [
    {
      "key": "field_640914eeec90a",
      "name": "hash",
      "type": "text",
      "parent": "group_63894140af6e3",
      "ID": 941,
      "label": "Hash",
      "aria-label": "",
      "prefix": "acf",
      "value": null,
      "menu_order": 0,
      "instructions": "",
      "required": 0,
      "id": "",
      "class": "",
      "conditional_logic": 0,
      "wrapper": {
        "width": "",
        "class": "",
        "id": ""
      },
      "default_value": "",
      "maxlength": "",
      "placeholder": "",
      "prepend": "",
      "append": "",
      "_name": "hash",
      "_valid": 1
    },
    {
      "key": "field_63894141c1f86",
      "name": "component_padding",
      "type": "select",
      "parent": "group_63894140af6e3",
      "ID": 942,
      "label": "Component Padding",
      "aria-label": "",
      "prefix": "acf",
      "value": null,
      "menu_order": 1,
      "instructions": "",
      "required": 0,
      "id": "",
      "class": "",
      "conditional_logic": 0,
      "wrapper": {
        "width": "33",
        "class": "",
        "id": ""
      },
      "choices": {
        "full": "Top Full / Bottom Full",
        "full-top-half-bottom": "Top Full / Bottom Half",
        "top-only-full": "Top Full / Bottom None",
        "half-top-full-bottom": "Top Half / Bottom Full",
        "half": "Top Half / Bottom Half",
        "top-only-half": "Top Half / Bottom None",
        "bottom-only-full": "Top None / Bottom Full",
        "bottom-only-half": "Top None / Bottom Half",
        "none": "None"
      },
      "default_value": "half",
      "return_format": "value",
      "multiple": 0,
      "allow_null": 0,
      "allow_in_bindings": 1,
      "ui": 0,
      "ajax": 0,
      "placeholder": "",
      "_name": "component_padding",
      "_valid": 1,
      "create_options": 0,
      "save_options": 0
    },
    {
      "key": "field_63894345c1f87",
      "name": "component_margins",
      "type": "select",
      "parent": "group_63894140af6e3",
      "ID": 943,
      "label": "Component Margins",
      "aria-label": "",
      "prefix": "acf",
      "value": null,
      "menu_order": 2,
      "instructions": "",
      "required": 0,
      "id": "",
      "class": "",
      "conditional_logic": 0,
      "wrapper": {
        "width": "33",
        "class": "",
        "id": ""
      },
      "choices": {
        "full": "Top Full / Bottom Full",
        "full-top-half-bottom": "Top Full / Bottom Half",
        "top-only-full": "Top Full / Bottom None",
        "half-top-full-bottom": "Top Half / Bottom Full",
        "half": "Top Half / Bottom Half",
        "top-only-half": "Top Half / Bottom None",
        "bottom-only-full": "Top None / Bottom Full",
        "bottom-only-half": "Top None / Bottom Half",
        "none": "None"
      },
      "default_value": "none",
      "return_format": "value",
      "multiple": 0,
      "allow_null": 0,
      "allow_in_bindings": 1,
      "ui": 0,
      "ajax": 0,
      "placeholder": "",
      "_name": "component_margins",
      "_valid": 1,
      "create_options": 0,
      "save_options": 0
    },
    {
      "key": "field_670813e18976a",
      "name": "hide_component",
      "type": "true_false",
      "parent": "group_63894140af6e3",
      "ID": 1318,
      "label": "Hide Component",
      "aria-label": "",
      "prefix": "acf",
      "value": null,
      "menu_order": 3,
      "instructions": "",
      "required": 0,
      "id": "",
      "class": "",
      "conditional_logic": 0,
      "wrapper": {
        "width": "33",
        "class": "",
        "id": ""
      },
      "message": "Check to hide a partially completed component.",
      "default_value": 0,
      "allow_in_bindings": 1,
      "ui": 0,
      "ui_on_text": "",
      "ui_off_text": "",
      "_name": "hide_component",
      "_valid": 1
    }
  ],
  "location": [
    [
      {
        "param": "post",
        "operator": "==",
        "value": "1024"
      }
    ]
  ],
  "menu_order": 0,
  "position": "normal",
  "style": "default",
  "label_placement": "top",
  "instruction_placement": "label",
  "hide_on_screen": "",
  "active": true,
  "description": "",
  "show_in_rest": 1,
  "_valid": true,
  "local": "json",
  "display_title": "",
  "local_file": "/var/www/vhosts/roostergrintemplates.com/api-gordon-acf-demo.roostergrintemplates.com/wp-content/themes/dist/acf-json/group_63894140af6e3.json"
}
